dacwinapi/__init__.py
dacwinapi/appuser.py
dacwinapi/base.py
dacwinapi/campaign.py
dacwinapi/event.py
dacwinapi/reward.py
dacwinapi/utils/Class.py
dacwinapi/utils/__init__.py
dacwinapi/utils/constants.py
dacwinapi/utils/models.py
dacwinapi-2.2.0.dist-info/LICENSE
dacwinapi-2.2.0.dist-info/METADATA
dacwinapi-2.2.0.dist-info/WHEEL
dacwinapi-2.2.0.dist-info/top_level.txt
dacwinapi-2.2.0.dist-info/RECORD
