Metadata-Version: 2.1
Name: dacwinapi
Version: 2.2.0
Summary: This package makes it easy to manage information about your DacWin referral system.
Author: DacTechnologies
Author-email: contact@dactechnologies.net
Requires-Python: >=3.9
License-File: LICENSE
